hasura/__init__.py
hasura/hasura_base.py
hasura-0.1.dist-info/DESCRIPTION.rst
hasura-0.1.dist-info/METADATA
hasura-0.1.dist-info/RECORD
hasura-0.1.dist-info/WHEEL
hasura-0.1.dist-info/metadata.json
hasura-0.1.dist-info/top_level.txt
